oauthAzureFastApi/__init__.py
oauthAzureFastApi/core.py
oauthAzureFastApi-0.4.16.dist-info/METADATA
oauthAzureFastApi-0.4.16.dist-info/WHEEL
oauthAzureFastApi-0.4.16.dist-info/top_level.txt
oauthAzureFastApi-0.4.16.dist-info/RECORD
