Metadata-Version: 2.1
Name: oauthAzureFastApi
Version: 0.4.16
Summary: A FastAPI module for Azure OAuth integration
Home-page: https://github.com/saubhik1/oauthAzureFastApi
Author: Saubhik Bhadra,Kaushik Bhadra
Author-email: saubhik.bhadra@gmail.com,kaushik.bhadra24@gmail.com
Classifier: Programming Language :: Python :: 3
Classifier: License :: OSI Approved :: MIT License
Classifier: Operating System :: OS Independent
Requires-Dist: fastapi
Requires-Dist: authlib
Requires-Dist: httpx
Requires-Dist: python-dotenv
Requires-Dist: python-jose
Requires-Dist: uvicorn
Requires-Dist: starlette
Requires-Dist: itsdangerous
